{
  "$schema": "https://mintlify.com/docs.json",
  "name": "Online Education Logs Analysis",
  "theme": "palm",
  "colors": {
    "primary": "#3B82F6",
    "light": "#60A5FA",
    "dark": "#1E40AF"
  },
  "navbar": {
    "primary": {
      "type": "github",
      "href": "https://github.com/jackie-0110/online-edu-logs-analysis"
    }
  },
  "footer": {
    "socials": {
      "github": "https://github.com/jackie-0110/online-edu-logs-analysis"
    }
  },
  "navigation": {
    "tabs": [
      {
        "tab": "Documentation",
        "groups": [
          {
            "group": "Overview",
            "pages": [
              "introduction",
              "abstract",
              "research-context"
            ]
          },
          {
            "group": "Getting Started",
            "pages": [
              "setup",
              "dependencies",
              "data-preparation"
            ]
          },
          {
            "group": "Methodology",
            "pages": [
              "methodology/overview",
              "methodology/kmeans-clustering",
              "methodology/regularized-least-squares"
            ]
          },
          {
            "group": "Implementation",
            "pages": [
              "implementation/feature-engineering",
              "implementation/model-training",
              "implementation/evaluation"
            ]
          },
          {
            "group": "Results",
            "pages": [
              "results/performance-metrics",
              "results/visualizations",
              "results/findings"
            ]
          }
        ]
      },
      {
        "tab": "API Reference",
        "groups": [
          {
            "group": "Core Functions",
            "pages": [
              "api/data-processing",
              "api/feature-functions",
              "api/model-functions",
              "api/evaluation-functions"
            ]
          }
        ]
      }
    ]
  }
}
